runai_model_streamer/__init__.py
runai_model_streamer/distributed_streamer/__init__.py
runai_model_streamer/distributed_streamer/distributed_streamer.py
runai_model_streamer/distributed_streamer/partition.py
runai_model_streamer/distributed_streamer/tests/__init__.py
runai_model_streamer/distributed_streamer/tests/dist_test_distributed_streamer.py
runai_model_streamer/distributed_streamer/tests/test_partition.py
runai_model_streamer/file_streamer/__init__.py
runai_model_streamer/file_streamer/file_streamer.py
runai_model_streamer/file_streamer/requests_iterator.py
runai_model_streamer/file_streamer/tests/__init__.py
runai_model_streamer/file_streamer/tests/test_file_streamer.py
runai_model_streamer/file_streamer/tests/test_requests_iterator.py
runai_model_streamer/libstreamer/__init__.py
runai_model_streamer/libstreamer/libstreamer.py
runai_model_streamer/libstreamer/lib/libstreamer.so
runai_model_streamer/libstreamer/tests/__init__.py
runai_model_streamer/libstreamer/tests/test_libstreamer.py
runai_model_streamer/s3_utils/__init__.py
runai_model_streamer/s3_utils/s3_utils.py
runai_model_streamer/safetensors_streamer/__init__.py
runai_model_streamer/safetensors_streamer/safetensors_pytorch.py
runai_model_streamer/safetensors_streamer/safetensors_streamer.py
runai_model_streamer/safetensors_streamer/streamer_mock.py
runai_model_streamer/safetensors_streamer/tests/__init__.py
runai_model_streamer/safetensors_streamer/tests/dist_test_safetensors_streamer.py
runai_model_streamer/safetensors_streamer/tests/test_mock.py
runai_model_streamer/safetensors_streamer/tests/test_safetensors_streamer.py
runai_model_streamer-0.15.5.dist-info/LICENSE
runai_model_streamer-0.15.5.dist-info/METADATA
runai_model_streamer-0.15.5.dist-info/WHEEL
runai_model_streamer-0.15.5.dist-info/top_level.txt
runai_model_streamer-0.15.5.dist-info/RECORD
