Metadata-Version: 2.1
Name: runai-model-streamer
Version: 0.15.5
Summary: UNKNOWN
Home-page: UNKNOWN
License: UNKNOWN
Platform: UNKNOWN
Requires-Dist: humanize
Requires-Dist: numpy
Requires-Dist: torch (<3.0.0,>=2.0.0)
Provides-Extra: gcs
Requires-Dist: runai-model-streamer-gcs (==0.15.5) ; extra == 'gcs'
Provides-Extra: s3
Requires-Dist: runai-model-streamer-s3 (==0.15.5) ; extra == 's3'
